ecli/__init__.py
ecli/cli.py
ecli/lib/__init__.py
ecli/lib/cryptography/__init__.py
ecli/lib/cryptography/aes.py
ecli/lib/cryptography/wincred.py
ecli/lib/defaults/__init__.py
ecli/lib/dictutils/__init__.py
ecli/lib/formatting/__init__.py
ecli/lib/input/__init__.py
ecli/lib/input/streams.py
ecli/lib/logger/__init__.py
ecli/lib/options/__init__.py
ecli/lib/options/mexclusive.py
ecli/lib/plugin/__init__.py
ecli/lib/plugin/finder.py
ecli/lib/plugin/metadata.py
ecli/lib/plugin/plugins.py
ecli/lib/proc/__init__.py
ecli/lib/proc/local_invocation.py
ecli/lib/shell/__init__.py
ecli/lib/shell/bash_init.py
ecli/lib/shell/which.py
bertdotecli-1.6.1.dist-info/LICENSE
bertdotecli-1.6.1.dist-info/METADATA
bertdotecli-1.6.1.dist-info/WHEEL
bertdotecli-1.6.1.dist-info/entry_points.txt
bertdotecli-1.6.1.dist-info/top_level.txt
bertdotecli-1.6.1.dist-info/RECORD
