Metadata-Version: 2.1
Name: bertdotecli
Version: 1.6.1
Summary: UNKNOWN
License: UNKNOWN
Platform: UNKNOWN
License-File: LICENSE
Requires-Dist: bs4 (<0.1,>=0.0.1)
Requires-Dist: click (<9.0,>=8.0)
Requires-Dist: click-plugins (<1.2,>=1.1.1)
Requires-Dist: colorama (<0.5,>=0.4.3)
Requires-Dist: first (<2.1,>=2.0.2)
Requires-Dist: bertdotconfig (<4.3.0,>=4.2.0)
Requires-Dist: paramiko (<2.8,>=2.7.0)
Requires-Dist: jello (<1.3,>=1.2.10)
Requires-Dist: requests (<2.23,>=2.22.0)
Requires-Dist: PyYAML (<6.0,>=5.3.1)
